musipy/__init__.py
musipy/add.py
musipy/subtract.py
musipy/additional/__init__.py
musipy/additional/divide.py
musipy/additional/multiply.py
musipy/extras/__init__.py
musipy/extras/divide.py
musipy/extras/multiply.py
musipy-0.0.3.dist-info/LICENSE
musipy-0.0.3.dist-info/METADATA
musipy-0.0.3.dist-info/WHEEL
musipy-0.0.3.dist-info/top_level.txt
musipy-0.0.3.dist-info/RECORD
